[
  {
    "chainId": 43114,
    "address": "0x260Bbf5698121EB85e7a74f2E45E16Ce762EbE11",
    "name": "Terra USD",
    "symbol": "UST",
    "decimals": 6,
    "commonKey": "uusd",
    "logoURI": "https://assets.coingecko.com/coins/images/12681/small/UST.png?1601612407"
  },
  {
    "chainId": 43114,
    "address": "0x120AD3e5A7c796349e591F1570D9f7980F4eA9cb",
    "name": "LUNA",
    "symbol": "LUNA",
    "decimals": 6,
    "commonKey": "uluna",
    "logoURI": "https://assets.coingecko.com/coins/images/8284/small/luna1557227471663.png?1567147072"
  },
  {
    "chainId": 1284,
    "address": "0x085416975fe14C2A731a97eC38B9bF8135231F62",
    "name": "Terra USD",
    "symbol": "UST",
    "decimals": 6,
    "commonKey": "uusd",
    "logoURI": "https://assets.coingecko.com/coins/images/12681/small/UST.png?1601612407"
  },
  {
    "chainId": 1284,
    "address": "0x31DAB3430f3081dfF3Ccd80F17AD98583437B213",
    "name": "LUNA",
    "symbol": "LUNA",
    "decimals": 6,
    "commonKey": "uluna",
    "logoURI": "https://assets.coingecko.com/coins/images/8284/small/luna1557227471663.png?1567147072"
  }
]
